training_results_visualizer/__init__.py
training_results_visualizer/__version__.py
training_results_visualizer/training_results_visualizer.py
training_results_visualizer-0.0.1.dist-info/METADATA
training_results_visualizer-0.0.1.dist-info/WHEEL
training_results_visualizer-0.0.1.dist-info/top_level.txt
training_results_visualizer-0.0.1.dist-info/RECORD
